[
  {
    "id": "kitchen-appliance-1",
    "title": "Smart Kitchen Blender with 6 Blades",

    "image": "../assets/img/kitchen/blender.jpg",
    "link": "https://www.amazon.es/dp/EXAMPLE1",
    "category": "Kitchen Appliances"
  },
  {
    "id": "kitchen-appliance-2",
    "title": "Air Fryer with Digital Display",

    "image": "../assets/img/kitchen/airfryer.jpg",
    "link": "https://www.amazon.es/dp/EXAMPLE2",
    "category": "Kitchen Appliances"

  },
  {
    "id": "kitchen-appliance-3",
    "title": "Multi-Cooker with 10-in-1 Functionality",

    "image": "../assets/img/kitchen/multicooker.jpg",
    "link": "https://www.amazon.es/dp/EXAMPLE3",
    "category": "Kitchen Appliances"
  }
]
